proteomics_downstream_analysis/__init__.py
proteomics_downstream_analysis/contamination.py
proteomics_downstream_analysis/dataqualityinformation.py
proteomics_downstream_analysis/dianndata.py
proteomics_downstream_analysis/dimensionalityreduction.py
proteomics_downstream_analysis/enrichmentanalysis.py
proteomics_downstream_analysis/imputer.py
proteomics_downstream_analysis/multileveldata.py
proteomics_downstream_analysis/preprocessing.py
proteomics_downstream_analysis/preprocessing_preprocessor.py
proteomics_downstream_analysis/preprocessor.py
proteomics_downstream_analysis/statistics.py
proteomics_downstream_analysis/utils.py
proteomics_downstream_analysis/visualizer.py
proteomics_downstream_analysis-0.1.3.dist-info/LICENSE
proteomics_downstream_analysis-0.1.3.dist-info/METADATA
proteomics_downstream_analysis-0.1.3.dist-info/WHEEL
proteomics_downstream_analysis-0.1.3.dist-info/top_level.txt
proteomics_downstream_analysis-0.1.3.dist-info/RECORD
