Metadata-Version: 2.1
Name: proteomics-downstream-analysis
Version: 0.1.3
Summary: A package for downstream data analysis of proteomics data
Home-page: https://github.com/vuductung/proteomics-downstream-anlaysis
Author: Vu Duc Tung
Author-email: tungvuduc@outlook.de
Keywords: proteomics,downstream analysis,data analysis,data visualization,mass spectrometry
Requires-Python: >=3.6.1
License-File: LICENSE
Requires-Dist: adjustText
Requires-Dist: goatools
Requires-Dist: gseapy
Requires-Dist: matplotlib
Requires-Dist: matplotlib-venn
Requires-Dist: numba
Requires-Dist: numpy
Requires-Dist: plotly
Requires-Dist: pyarrow
Requires-Dist: pycirclize
Requires-Dist: pyteomics
Requires-Dist: scikit-learn
Requires-Dist: scipy
Requires-Dist: seaborn
Requires-Dist: statsmodels
Requires-Dist: streamlit
Requires-Dist: umap
Requires-Dist: UpSetPlot
Requires-Dist: venn
